setup.py
freeverse/__init__.py
freeverse/expectations.py
freeverse/freeverse.py
freeverse.egg-info/PKG-INFO
freeverse.egg-info/SOURCES.txt
freeverse.egg-info/dependency_links.txt
freeverse.egg-info/not-zip-safe
freeverse.egg-info/top_level.txt