Metadata-Version: 1.0
Name: freeverse
Version: 0.0.0
Summary: A new way to write free-form, minimalistic specs (tests) in Python that favor natural language
Home-page: https://github.com/Kazark/pyfreeverse
Author: Kazark
Author-email: kazark@zoho.com
License: MIT
Platform: UNKNOWN
